invisibleroads_uploads/__init__.py
invisibleroads_uploads/models.py
invisibleroads_uploads/tests.py
invisibleroads_uploads/views.py
invisibleroads_uploads/assets/part.min.css
invisibleroads_uploads/assets/part.min.js
invisibleroads_uploads/templates/parts.jinja2
invisibleroads_uploads-0.4.2.4.dist-info/DESCRIPTION.rst
invisibleroads_uploads-0.4.2.4.dist-info/METADATA
invisibleroads_uploads-0.4.2.4.dist-info/RECORD
invisibleroads_uploads-0.4.2.4.dist-info/WHEEL
invisibleroads_uploads-0.4.2.4.dist-info/metadata.json
invisibleroads_uploads-0.4.2.4.dist-info/top_level.txt
