Metadata-Version: 2.0
Name: invisibleroads-uploads
Version: 0.4.2.4
Summary: File upload functionality
Home-page: https://github.com/invisibleroads/invisibleroads-uploads
Author: Roy Hyunjin Han
Author-email: rhh@crosscompute.com
License: UNKNOWN
Keywords: web wsgi bfg pylons pyramid invisibleroads
Platform: UNKNOWN
Classifier: Programming Language :: Python
Classifier: Framework :: Pyramid
Classifier: Topic :: Internet :: WWW/HTTP :: WSGI :: Application
Requires-Dist: invisibleroads-macros (>=0.9.5.1)
Requires-Dist: invisibleroads-posts (>=0.6.1)
Requires-Dist: pyramid
Requires-Dist: pytest
Requires-Dist: six
